seamster/__init__.py
seamster/__main__.py
seamster/join.py
seamster/join_side.py
seamster/validate.py
seamster-0.0.1.dist-info/LICENSE
seamster-0.0.1.dist-info/METADATA
seamster-0.0.1.dist-info/WHEEL
seamster-0.0.1.dist-info/entry_points.txt
seamster-0.0.1.dist-info/top_level.txt
seamster-0.0.1.dist-info/RECORD
