Metadata-Version: 2.1
Name: seamster
Version: 0.0.1
Summary: High Performance Fuzzy Business Entity Matching
Home-page: http://gitlab.com/juniperlabs-foss/seamster
Author: Juniper Labs
Author-email: support@juniperlabs.io
License: Apache 2.0
Download-URL: https://gitlab.com/juniperlabs-foss/seamster/repository/archive.tar.gz?ref=master
Keywords: seamster
Platform: UNKNOWN
Classifier: Development Status :: 3 - Alpha
Classifier: Operating System :: POSIX :: Linux
Classifier: License :: OSI Approved :: Apache Software License
Classifier: Natural Language :: English
Classifier: Environment :: Console
Classifier: Intended Audience :: End Users/Desktop
Classifier: Programming Language :: Python :: 3
Classifier: Programming Language :: Python :: 3.5
Classifier: Programming Language :: Python :: 3.6
Classifier: Programming Language :: Python :: 3.7
Requires-Python: >=3.5
Requires-Dist: typing (>=3.7.4)
Requires-Dist: sparse-dot-topn (>=0.2.6)
Requires-Dist: pandas (>=0.25.0)
Requires-Dist: scikit-learn (>=0.21.3)
